hyperparameter-0.6.0.dist-info/METADATA
hyperparameter-0.6.0.dist-info/WHEEL
hyperparameter-0.6.0.dist-info/entry_points.txt
hyperparameter-0.6.0.dist-info/license_files/LICENSE
hyperparameter/analyzer.py
hyperparameter/__init__.py
hyperparameter/api.py
hyperparameter/cli.py
hyperparameter/loader.py
hyperparameter/tune.py
hyperparameter/examples/__init__.py
hyperparameter/examples/quickstart.py
hyperparameter/storage.py
hyperparameter/librbackend.abi3.so
hyperparameter-0.6.0.dist-info/RECORD
