Metadata-Version: 2.1
Name: hyperparameter
Version: 0.6.0
Requires-Dist: toml >=0.10
License-File: LICENSE
Summary: A hyper-parameter library for researchers, data scientists and machine learning engineers.
Author-email: Reiase <reiase@gmail.com>
License: Apache License Version 2.0
Requires-Python: >=3.7
